pyseqr/__init__.py
pyseqr/core.py
tests/__init__.py
tests/test_core.py
pyseqr-0.1.0.dist-info/LICENSE
pyseqr-0.1.0.dist-info/METADATA
pyseqr-0.1.0.dist-info/WHEEL
pyseqr-0.1.0.dist-info/top_level.txt
pyseqr-0.1.0.dist-info/RECORD
