Metadata-Version: 2.1
Name: pyseqr
Version: 0.1.0
Summary: A Python library for sequence search and analysis.
Home-page: https://github.com/rattling/pyseqr
Author: John Curry
Classifier: Programming Language :: Python :: 3
Classifier: License :: OSI Approved :: Apache Software License
Classifier: Operating System :: OS Independent
Requires-Python: >=3.7
License-File: LICENSE
